[
  {
    "original": "viana 1.png",
    "optimized": "viana-001.jpg"
  },
  {
    "original": "viana 2.png",
    "optimized": "viana-002.jpg"
  },
  {
    "original": "viana 3.png",
    "optimized": "viana-003.jpg"
  },
  {
    "original": "viana 4.png",
    "optimized": "viana-004.jpg"
  },
  {
    "original": "viana 5.png",
    "optimized": "viana-005.jpg"
  },
  {
    "original": "viana 6.png",
    "optimized": "viana-006.jpg"
  },
  {
    "original": "viana 7.png",
    "optimized": "viana-007.jpg"
  }
]